{
  "$schema": "https://json-schema.org/draft-07/schema",
  "title": "Learning Path",
  "type": "object",
  "properties": {
    "id": {
      "type": "integer"
    },
    "name": {
      "type": "string"
    },
    "slug": {
      "type": "string"
    },
    "description": {
      "type": "string"
    },
    "tags": {
      "type": "array",
      "items": {
        "type": "string"
      }
    },
    "tutorials": {
      "type": "array",
      "items": {
        "type": "string"
      }
    }
  }
}
